lindo/LSconst.py
lindo/__init__.py
lindo/lindo.cp38-win32.pyd
lindo/loadLibs.py
lindo/wrappers.py
lindo_test/__init__.py
lindo_test/__main__.py
lindo_test/test.py
lindo-16.0.68.dist-info/LICENSE
lindo-16.0.68.dist-info/METADATA
lindo-16.0.68.dist-info/WHEEL
lindo-16.0.68.dist-info/top_level.txt
lindo-16.0.68.dist-info/RECORD
