Metadata-Version: 2.1
Name: lindo
Version: 16.0.68
Summary: Python interface to LINDO API
Home-page: http://www.lindo.com
Author: Lindo Systems, Inc.
Author-email: support@lindo.com
Classifier: Programming Language :: Python :: 3
Classifier: Programming Language :: Python :: 3.7
Classifier: Programming Language :: Python :: 3.8
Classifier: Programming Language :: Python :: 3.9
Classifier: Programming Language :: Python :: 3.10
Classifier: Programming Language :: Python :: 3 :: Only
Requires-Python: >=3.7
License-File: LICENSE
Requires-Dist: numpy
